evo/data_converters/vtk/__init__.py
evo/data_converters/vtk/importer/__init__.py
evo/data_converters/vtk/importer/_utils.py
evo/data_converters/vtk/importer/exceptions.py
evo/data_converters/vtk/importer/vtk_attributes_to_evo.py
evo/data_converters/vtk/importer/vtk_attributes_to_grid.py
evo/data_converters/vtk/importer/vtk_image_data_to_evo.py
evo/data_converters/vtk/importer/vtk_rectilinear_grid_to_evo.py
evo/data_converters/vtk/importer/vtk_to_evo.py
evo/data_converters/vtk/importer/vtk_unstructured_grid_to_evo.py
evo_data_converters_vtk-0.1.4.dist-info/METADATA
evo_data_converters_vtk-0.1.4.dist-info/WHEEL
evo_data_converters_vtk-0.1.4.dist-info/licenses/LICENSE.md
evo_data_converters_vtk-0.1.4.dist-info/RECORD
